Workbook

Sheet Sign-off
A1: Field | B1: Value
A2: Project | B2: RentCollection (ALRTAM)
A3: Sprint / Version | B3: Sprint 23
A4: Test cycle | B4: Cycle ___ of ___
A5: Tester name
A6: Build / commit hash
A7: Environment | B7: demo / pre-prod / prod
A8: Browser
A9: Start date
A10: End date
A11: Sign-off (tester)
A12: Sign-off (TL)
A13: Sign-off (PM)

Sheet Summary
A1: Section | B1: Total | C1: P0 | D1: P1 | E1: P2 | F1: Pass | G1: Fail | H1: Blocked | I1: Not Run | J1: Percent Done
A2: 0. Smoke Pack | B2: 7 | C2: 4 | D2: 3 | E2: 0 | F2: =COUNTIF('0. Smoke Pack'!H:H,"Pass") | G2: =COUNTIF('0. Smoke Pack'!H:H,"Fail") | H2: =COUNTIF('0. Smoke Pack'!H:H,"Blocked") | I2: =B2-F2-G2-H2 | J2: =IF(B2=0,0,(F2+G2+H2)/B2)
A3: 1. Authentication | B3: 10 | C3: 5 | D3: 3 | E3: 2 | F3: =COUNTIF('1. Authentication'!H:H,"Pass") | G3: =COUNTIF('1. Authentication'!H:H,"Fail") | H3: =COUNTIF('1. Authentication'!H:H,"Blocked") | I3: =B3-F3-G3-H3 | J3: =IF(B3=0,0,(F3+G3+H3)/B3)
A4: 2. Property Module | B4: 11 | C4: 4 | D4: 6 | F4: =COUNTIF('2. Property Module'!H:H,"Pass") | G4: =COUNTIF('2. Property Module'!H:H,"Fail") | H4: =COUNTIF('2. Property Module'!H:H,"Blocked") | I4: =B4-F4-G4-H4 | J4: =IF(B4=0,0,(F4+G4+H4)/B4)
A5: 3. Unit Module | B5: 5 | C5: 3 | D5: 2 | E5: 0 | F5: =COUNTIF('3. Unit Module'!H:H,"Pass") | G5: =COUNTIF('3. Unit Module'!H:H,"Fail") | H5: =COUNTIF('3. Unit Module'!H:H,"Blocked") | I5: =B5-F5-G5-H5 | J5: =IF(B5=0,0,(F5+G5+H5)/B5)
A6: 4. Tenant + Civil ID | B6: 14 | C6: 6 | D6: 7 | F6: =COUNTIF('4. Tenant + Civil ID'!H:H,"Pass") | G6: =COUNTIF('4. Tenant + Civil ID'!H:H,"Fail") | H6: =COUNTIF('4. Tenant + Civil ID'!H:H,"Blocked") | I6: =B6-F6-G6-H6 | J6: =IF(B6=0,0,(F6+G6+H6)/B6)
A7: 5. Lease Module | B7: 12 | C7: 7 | D7: 4 | F7: =COUNTIF('5. Lease Module'!H:H,"Pass") | G7: =COUNTIF('5. Lease Module'!H:H,"Fail") | H7: =COUNTIF('5. Lease Module'!H:H,"Blocked") | I7: =B7-F7-G7-H7 | J7: =IF(B7=0,0,(F7+G7+H7)/B7)
A8: 6. Invoices | B8: 6 | C8: 3 | D8: 3 | E8: 0 | F8: =COUNTIF('6. Invoices'!H:H,"Pass") | G8: =COUNTIF('6. Invoices'!H:H,"Fail") | H8: =COUNTIF('6. Invoices'!H:H,"Blocked") | I8: =B8-F8-G8-H8 | J8: =IF(B8=0,0,(F8+G8+H8)/B8)
A9: 7. Payments | B9: 11 | C9: 6 | D9: 5 | E9: 0 | F9: =COUNTIF('7. Payments'!H:H,"Pass") | G9: =COUNTIF('7. Payments'!H:H,"Fail") | H9: =COUNTIF('7. Payments'!H:H,"Blocked") | I9: =B9-F9-G9-H9 | J9: =IF(B9=0,0,(F9+G9+H9)/B9)
A10: 8. Maintenance | B10: 5 | C10: 2 | D10: 2 | F10: =COUNTIF('8. Maintenance'!H:H,"Pass") | G10: =COUNTIF('8. Maintenance'!H:H,"Fail") | H10: =COUNTIF('8. Maintenance'!H:H,"Blocked") | I10: =B10-F10-G10-H10 | J10: =IF(B10=0,0,(F10+G10+H10)/B10)
A11: 9. Documents | B11: 6 | C11: 0 | D11: 5 | F11: =COUNTIF('9. Documents'!H:H,"Pass") | G11: =COUNTIF('9. Documents'!H:H,"Fail") | H11: =COUNTIF('9. Documents'!H:H,"Blocked") | I11: =B11-F11-G11-H11 | J11: =IF(B11=0,0,(F11+G11+H11)/B11)
A12: 10. Reports | B12: 5 | D12: 4 | E12: 0 | F12: =COUNTIF('10. Reports'!H:H,"Pass") | G12: =COUNTIF('10. Reports'!H:H,"Fail") | H12: =COUNTIF('10. Reports'!H:H,"Blocked") | I12: =B12-F12-G12-H12 | J12: =IF(B12=0,0,(F12+G12+H12)/B12)
A13: 11. Tenant Portal | B13: 8 | C13: 6 | D13: 2 | E13: 0 | F13: =COUNTIF('11. Tenant Portal'!H:H,"Pass") | G13: =COUNTIF('11. Tenant Portal'!H:H,"Fail") | H13: =COUNTIF('11. Tenant Portal'!H:H,"Blocked") | I13: =B13-F13-G13-H13 | J13: =IF(B13=0,0,(F13+G13+H13)/B13)
A14: 12. Role-Based Access | B14: 10 | C14: 7 | D14: 3 | E14: 0 | F14: =COUNTIF('12. Role-Based Access'!H:H,"Pass") | G14: =COUNTIF('12. Role-Based Access'!H:H,"Fail") | H14: =COUNTIF('12. Role-Based Access'!H:H,"Blocked") | I14: =B14-F14-G14-H14 | J14: =IF(B14=0,0,(F14+G14+H14)/B14)
A15: 13. Edge Cases | B15: 10 | C15: 2 | D15: 5 | E15: 3 | F15: =COUNTIF('13. Edge Cases'!H:H,"Pass") | G15: =COUNTIF('13. Edge Cases'!H:H,"Fail") | H15: =COUNTIF('13. Edge Cases'!H:H,"Blocked") | I15: =B15-F15-G15-H15 | J15: =IF(B15=0,0,(F15+G15+H15)/B15)
A16: 14. Performance | B16: 6 | C16: 0 | D16: 6 | E16: 0 | F16: =COUNTIF('14. Performance'!H:H,"Pass") | G16: =COUNTIF('14. Performance'!H:H,"Fail") | H16: =COUNTIF('14. Performance'!H:H,"Blocked") | I16: =B16-F16-G16-H16 | J16: =IF(B16=0,0,(F16+G16+H16)/B16)
A17: TOTAL | B17: 126 | C17: 55 | D17: 60 | E17: 5 | F17: =SUM(F2:F16) | G17: =SUM(G2:G16) | H17: =SUM(H2:H16) | I17: =SUM(I2:I16) | J17: =IF(B17=0,0,(F17+G17+H17)/B17)

Sheet 0. Smoke Pack
A1: ID | B1: Title | C1: Priority | D1: Preconditions | E1: Steps | F1: Expected Result | G1: Actual Result | H1: Result | I1: Tester | J1: Date | K1: Bug ID | L1: Notes
A2: SMK-01 | B2: Login page renders | C2: P0 | D2: Logged out | E2: Visit /Account/Login | F2: Page loads with ALRTAM logo + Civil ID + Email fields visible
A3: SMK-02 | B3: Admin can sign in | C3: P0 | D3: On login page | E3: Click Fill demo credentials then Sign in | F3: Redirects to /Dashboard, sidebar visible, user name top-right
A4: SMK-03 | B4: Dashboard KPIs load | C4: P0 | D4: Logged in as Admin | E4: View /Dashboard | F4: Tiles show numbers (not dashes or error icons)
A5: SMK-04 | B5: ALRTAM logo top-right | C5: P1 | D5: Logged in | E5: View top header | F5: ALRATM logo visible on right of top header
A6: SMK-05 | B6: Tenant Create page renders | C6: P0 | D6: Logged in | E6: Sidebar then Tenants then Add Tenant | F6: 3 zones visible: Essentials (open), More details (collapsed), Documents
A7: SMK-06 | B7: Tenant portal login renders | C7: P1 | D7: Logged out | E7: Go to /TenantPortal/Login | F7: Tenant-styled login page renders
A8: SMK-07 | B8: Logout works | C8: P1 | D8: Logged in | E8: Top-right user dropdown then Logout | F8: Redirects back to login page

Sheet 1. Authentication
A1: ID | B1: Title | C1: Priority | D1: Preconditions | E1: Steps | F1: Expected Result | G1: Actual Result | H1: Result | I1: Tester | J1: Date | K1: Bug ID | L1: Notes
A2: AUTH-01 | B2: Valid admin login | C2: P0 | D2: Logged out | E2: Enter admin@test.com / Admin@123 then Sign in | F2: Redirected to Dashboard
A3: AUTH-02 | B3: Invalid password | C3: P0 | D3: Logged out | E3: Enter admin@test.com / wrong then Sign in | F3: Same page, red error Invalid email or password
A4: AUTH-03 | B4: Empty email validation | C4: P1 | D4: Logged out | E4: Leave email blank then Sign in | F4: Inline validation Required below field
A5: AUTH-04 | B5: Demo credentials auto-fills | C5: P1 | D5: Logged out | E5: Click Fill demo credentials | F5: Email and password fields populated
A6: AUTH-05 | B6: Show / hide password toggle | C6: P2 | D6: Logged out | E6: Type password then click eye icon | F6: Password becomes visible; icon flips to crossed-eye
A7: AUTH-06 | B7: Remember-me 12h persistence | C7: P1 | D7: Logged in | E7: Tick Remember me then Sign in, close browser, reopen, visit /Dashboard | F7: Still logged in (no redirect to login)
A8: AUTH-07 | B8: Forgot password link | C8: P2 | D8: Logged out | E8: Click Forgot password | F8: /Account/ForgotPassword opens, email input shown
A9: AUTH-08 | B9: Tenant blocked from staff portal | C9: P0 | D9: Logged out | E9: At /Account/Login enter tenant credentials | F9: Rejected: This account is a tenant; use the tenant portal
A10: AUTH-09 | B10: Logout drops auth cookie | C10: P0 | D10: Logged in | E10: Top-right then Logout | F10: Cookie removed, redirected to login, sidebar gone
A11: AUTH-10 | B11: Direct URL while logged out redirects | C11: P0 | D11: Logged out | E11: Visit /Properties directly | F11: 302 to /Account/Login?ReturnUrl=/Properties

Sheet 2. Property Module
A1: ID | B1: Title | C1: Priority | D1: Preconditions | E1: Steps | F1: Expected Result | G1: Actual Result | H1: Result | I1: Tester | J1: Date | K1: Bug ID | L1: Notes
A2: PROP-01 | B2: Property list loads | C2: P0 | D2: Logged in as Admin | E2: Sidebar then Properties | F2: Grid of cards or table with KPI tiles at top
A3: PROP-02 | B3: Create property Essentials only | C3: P0 | D3: On /Properties | E3: Click Add Property, fill Name + PACI + Type=Apartment + Governorate + Units=10 + Company, Save | F3: Redirected to Index, new property in list
A4: PROP-03 | B4: Required field missing blocks save | C4: P0 | D4: On Create form | E4: Leave PACI blank then Save | F4: Inline error chip Required under PACI; no save
A5: PROP-04 | B5: More details toggle | C5: P1 | D5: On Create form | E5: Click More details caret | F5: Section expands, Address/Valuation/Management fields shown
A6: PROP-05 | B6: Save and add another | C6: P1 | D6: On Create form | E6: Fill Essentials then click Save and add another | F6: Form clears, green chip Property X saved
A7: PROP-06 | B7: Draft autosave and restore | C7: P2 | D7: On Create form | E7: Type Name + PACI, close tab, reopen Create form | F7: Fields pre-populated, green Draft restored chip
A8: PROP-07 | B8: Upload document on create | C8: P1 | D8: On Create form | E8: Fill Essentials then Documents zone with Type=Deed and a PDF, Save | F8: Property saved, Document linked in /Documents
A9: PROP-08 | B9: Edit property | C9: P1 | D9: Property exists | E9: Open property then Edit, change Name, Save | F9: List shows new name
A10: PROP-09 | B10: Property details page | C10: P1 | D10: Property exists | E10: Click row | F10: Details shows all fields, attached units, documents
A11: PROP-10 | B11: Delete blocked when units exist | C11: P1 | D11: Property with units | E11: Try Delete | F11: Blocked: Cannot delete property with active units
A12: PROP-11 | B12: Duplicate PACI rejected | C12: P0 | D12: Property with PACI=X exists | E12: Create another property with PACI=X | F12: Friendly error (not 500): A property with this PACI already exists

Sheet 3. Unit Module
A1: ID | B1: Title | C1: Priority | D1: Preconditions | E1: Steps | F1: Expected Result | G1: Actual Result | H1: Result | I1: Tester | J1: Date | K1: Bug ID | L1: Notes
A2: UNIT-01 | B2: Unit list loads | C2: P0 | D2: Logged in | E2: Sidebar then Units | F2: Table loads, Add button visible top-right
A3: UNIT-02 | B3: Create unit without rent | C3: P1 | D3: Property exists | E3: New Unit, fill Number and Bedrooms, leave MonthlyRent blank, Save | F3: Saves (rent optional at unit-level)
A4: UNIT-03 | B4: Duplicate Property+UnitNumber blocked | C4: P0 | D4: Unit exists | E4: Create unit with same Property + UnitNumber | F4: Friendly error, not SqlException
A5: UNIT-04 | B5: Unit status reflects active lease | C5: P0 | D5: Active lease on unit | E5: Open unit details | F5: Status = Occupied (not Vacant)
A6: UNIT-05 | B6: Lease pre-fill from Unit | C6: P1 | D6: Vacant unit | E6: Open vacant unit then click Create Lease | F6: /Leases/Create?unitId=X opens with Property + Unit pre-selected

Sheet 4. Tenant + Civil ID
A1: ID | B1: Title | C1: Priority | D1: Preconditions | E1: Steps | F1: Expected Result | G1: Actual Result | H1: Result | I1: Tester | J1: Date | K1: Bug ID | L1: Notes
A2: TEN-01 | B2: Tenant list loads | C2: P0 | D2: Logged in | E2: Sidebar then Tenants | F2: Table with KPIs at top
A3: TEN-02 | B3: Civil ID format validation | C3: P0 | D3: On Create form | E3: Type Civil ID = 12345 then Tab out | F3: Red chip Civil ID must be 12 digits
A4: TEN-03 | B4: Civil ID checksum + DOB auto-fill | C4: P0 | D4: On Create form | E4: Enter valid 12-digit Civil ID | F4: Green chip Civil ID validated DOB pre-filled, DOB populated
A5: TEN-04 | B5: Civil ID checksum mismatch warning | C5: P1 | D5: On Create form | E5: Enter 12-digit ID with wrong checksum | F5: Amber Checksum mismatch double-check the number, DOB still pre-filled
A6: TEN-05 | B6: Civil ID scan requires consent | C6: P1 | D6: Gemini enabled | E6: Click Scan card without ticking consent | F6: Red message Please tick the consent box first
A7: TEN-06 | B7: Civil ID scan fills name + DOB | C7: P1 | D7: Gemini enabled | E7: Tick consent then click Scan card then upload Civil ID image | F7: Status Reading card then green Card read; First/Last Name, DOB filled with amber border
A8: TEN-07 | B8: Civil ID scan rejects oversized file | C8: P1 | D8: Gemini enabled | E8: Upload a 6 MB file | F8: Red File too large max 5 MB
A9: TEN-08 | B9: Civil ID enrichment disabled message | C9: P2 | D9: Gemini disabled | E9: Try to scan | F9: Civil ID enrichment is disabled contact admin
A10: TEN-09 | B10: Required Essentials block save | C10: P0 | D10: On Create form | E10: Leave First Name blank then Save | F10: Red chip on First Name; no save
A11: TEN-10 | B11: CompanyId auto-assigned (no picker) | C11: P0 | D11: Logged in as Admin | E11: New Tenant form | F11: No Company picker visible; on save tenant gets admin CompanyId
A12: TEN-11 | B12: Tenant document upload on create | C12: P1 | D12: On Create form | E12: Add document Type=Civil ID + file, Save | F12: Document linked to tenant, visible in /Documents
A13: TEN-12 | B13: Save and add another (Tenant) | C13: P1 | D13: On Create form | E13: Click Save and add another | F13: Form clears, green chip Tenant X saved
... A15: TEN-14 | B15: Cross-company isolation | C15: P0 | D15: 2 admins from 2 cos | E15: Admin from Co A opens /Tenants/Details/{id-from-Co-B} | F15: 404 or 403 never Co B data

Sheet 5. Lease Module
A1: ID | B1: Title | C1: Priority | D1: Preconditions | E1: Steps | F1: Expected Result | G1: Actual Result | H1: Result | I1: Tester | J1: Date | K1: Bug ID | L1: Notes
A2: LSE-01 | B2: Lease list loads | C2: P0 | D2: Logged in | E2: Sidebar then Leases | F2: Active leases table loads
A3: LSE-02 | B3: Create lease happy path (no deposit) | C3: P0 | D3: Vacant unit + tenant | E3: New Lease, pick Building then Unit then Tenant, dates, rent=300, deposit=0, Save | F3: Saved as Active; unit Occupied; redirect to Index
A4: LSE-03 | B4: Create lease with deposit then Pending | C4: P0 | D4: Vacant unit + tenant | E4: Same as LSE-02 but deposit=500 | F4: Saved as Pending; banner issue deposit invoice via Activate
A5: LSE-04 | B5: Building then Unit cascade filters | C5: P1 | D5: Multiple buildings | E5: Pick Building A then check Unit dropdown | F5: Only Building A vacant units shown
A6: LSE-05 | B6: Cannot lease occupied unit | C6: P0 | D6: Occupied unit | E6: Create another lease on same unit | F6: Friendly error, not duplicate-key SqlException
A7: LSE-06 | B7: End date after start date | C7: P0 | D7: New form | E7: Set end date before start date, Save | F7: Validation error chip
A8: LSE-07 | B8: Insurance None means no insurance | C8: P1 | D8: New form | E8: Frequency=None, Save | F8: Saves; no insurance invoices
A9: LSE-08 | B9: Insurance Monthly | C9: P1 | D9: New form | E9: Frequency=Monthly Amount=10, Save, trigger daily job | F9: Monthly insurance invoice issued separate from rent
A10: LSE-09 | B10: Activate Pending lease | C10: P0 | D10: Pending lease | E10: Open lease then Activate | F10: Status Active; deposit invoice issued; unit Occupied
A11: LSE-10 | B11: Terminate active lease | C11: P0 | D11: Active lease | E11: Open lease then Terminate, enter reason, Confirm | F11: Status Terminated; unit Vacant; refund record queued
A12: LSE-11 | B12: Lease document upload on create | C12: P1 | D12: New form | E12: Add Signed Lease PDF, Save | F12: PDF linked to lease in /Documents
A13: LSE-12 | B13: Save and add another (Lease) | C13: P2 | D13: New form | E13: Click Save and add another | F13: Form clears, green chip Lease saved

Sheet 6. Invoices
A1: ID | B1: Title | C1: Priority | D1: Preconditions | E1: Steps | F1: Expected Result | G1: Actual Result | H1: Result | I1: Tester | J1: Date | K1: Bug ID | L1: Notes
A2: INV-01 | B2: Invoice list loads | C2: P0 | D2: Logged in | E2: Sidebar then Invoices | F2: Table, filters (Status, Date, Tenant), totals KPIs
A3: INV-02 | B3: Daily rent invoicing creates invoice | C3: P0 | D3: Active lease DueDay=today | E3: Wait for 02:00 UTC job or trigger via /hangfire | F3: New invoice type=Rent for today amount appears
A4: INV-03 | B4: No double-invoicing on job retry | C4: P0 | D4: After INV-02 | E4: Trigger the job again | F4: No duplicate invoice (idempotency)
A5: INV-04 | B5: Late fee added after grace period | C5: P1 | D5: Unpaid invoice past due | E5: Wait for late-fee job (02:30 UTC) | F5: New invoice type=LateFee amount = LateFeeAmount
A6: INV-05 | B6: Invoice PDF generates | C6: P1 | D6: Open invoice | E6: Click Download PDF | F6: Branded PDF (gold + black, ALRTAM logo, 3-decimal KWD)
A7: INV-06 | B7: Invoice email queued | C7: P1 | D7: New invoice issued | E7: Check Notifications table | F7: Pending notification of channel=Email exists

Sheet 7. Payments
A1: ID | B1: Title | C1: Priority | D1: Preconditions | E1: Steps | F1: Expected Result | G1: Actual Result | H1: Result | I1: Tester | J1: Date | K1: Bug ID | L1: Notes
A2: PAY-C-01 | B2: Record cash payment | C2: P0 | D2: Unpaid invoice | E2: Open invoice then Record Cash, enter amount + receipt no, Save | F2: Payment Confirmed; invoice Paid; balance = 0
A3: PAY-C-02 | B3: Cash partial payment | C3: P1 | D3: Unpaid invoice (300) | E3: Enter amount=200 | F3: Invoice PartiallyPaid balance=100
A4: PAY-C-03 | B4: Cash overpayment rejected | C4: P1 | D4: Unpaid invoice (300) | E4: Enter amount=400 | F4: Friendly error Amount exceeds invoice balance
A5: PAY-B-01 | B5: Tenant uploads transfer screenshot | C5: P0 | D5: Tenant + invoice | E5: Open invoice then Pay by Bank Transfer, upload PNG, Submit | F5: Payment Pending Approval; invoice unchanged
A6: PAY-B-02 | B6: Accountant sees in approval queue | C6: P0 | D6: After PAY-B-01 | E6: Accountant then /PaymentApproval | F6: Row shows tenant, amount, screenshot link
A7: PAY-B-03 | B7: Approve bank transfer | C7: P0 | D7: Pending in queue | E7: Open row then Approve | F7: Payment Confirmed; invoice Paid; receipt email queued
A8: PAY-B-04 | B8: Reject bank transfer with note | C8: P1 | D8: Pending in queue | E8: Open row then Reject, enter note, Submit | F8: Payment Rejected; tenant sees note in portal
A9: PAY-K-01 | B9: K-NET sandbox happy path | C9: P0 | D9: UseSandbox=true, invoice | E9: Pay with K-NET, use test card, return | F9: Returned to /api/payments/knet/response; payment Confirmed
A10: PAY-K-02 | B10: K-NET cancelled by user | C10: P1 | D10: Same | E10: On K-NET form click Cancel | F10: Returned to error URL; invoice unchanged
A11: PAY-K-03 | B11: K-NET duplicate guard | C11: P0 | D11: Same | E11: Submit same payment twice within 1s | F11: Second rejected by PaymentIdempotencies
A12: PAY-K-04 | B12: K-NET reconciliation recovers | C12: P1 | D12: Unknown K-NET payment | E12: Wait for 03:00 UTC reconcile job | F12: Status updated based on gateway truth

Sheet 8. Maintenance
A1: ID | B1: Title | C1: Priority | D1: Preconditions | E1: Steps | F1: Expected Result | G1: Actual Result | H1: Result | I1: Tester | J1: Date | K1: Bug ID | L1: Notes
A2: MNT-01 | B2: Tenant raises request | C2: P0 | D2: Tenant logged in | E2: Tenant portal then Maintenance then New, fill issue + photo, Submit | F2: Request in /Maintenance with status=Open
A3: MNT-02 | B3: Manager assigns vendor | C3: P0 | D3: Open request | E3: Open request then Assign, pick vendor + priority + ETA, Save | F3: Status Assigned, vendor name shown
A4: MNT-03 | B4: Mark complete with photos | C4: P1 | D4: Assigned request | E4: Open then Mark Complete, upload after-photos + cost, Save | F4: Status Completed; cost stored
A5: MNT-04 | B5: Photos visible to tenant | C5: P1 | D5: Completed request | E5: Tenant portal then request | F5: Tenant sees before + after photos
A6: MNT-05 | B6: Dashboard open-maint KPI accurate | C6: P2 | D6: Several requests | E6: Compare KPI to /Maintenance Open filter | F6: Numbers match

Sheet 9. Documents
A1: ID | B1: Title | C1: Priority | D1: Preconditions | E1: Steps | F1: Expected Result | G1: Actual Result | H1: Result | I1: Tester | J1: Date | K1: Bug ID | L1: Notes
A2: DOC-01 | B2: Document browser loads | C2: P1 | D2: Logged in | E2: Sidebar then Documents | F2: List of documents, filter by Type/Entity
A3: DOC-02 | B3: Download document | C3: P1 | D3: Document exists | E3: Click row then Download | F3: File downloads, opens
A4: DOC-03 | B4: Doc linked to multiple entities | C4: P2 | D4: Civil ID on tenant + lease | E4: Open document details | F4: Linked to list shows both
A5: DOC-04 | B5: Delete document removes file | C5: P1 | D5: Document exists | E5: Delete | F5: File gone from disk + DB; cascade DocumentLink rows
A6: DOC-05 | B6: Reject oversized upload | C6: P1 | D6: New form | E6: Upload 12 MB file | F6: Friendly error, not 500
A7: DOC-06 | B7: Reject wrong extension | C7: P1 | D7: New form | E7: Upload .exe | F7: Friendly error

Sheet 10. Reports
A1: ID | B1: Title | C1: Priority | D1: Preconditions | E1: Steps | F1: Expected Result | G1: Actual Result | H1: Result | I1: Tester | J1: Date | K1: Bug ID | L1: Notes
A2: RPT-01 | B2: Rent collection by month Excel | C2: P1 | D2: Logged in | E2: Reports then Rent Collection, pick date range, Export Excel | F2: .xlsx downloads, opens cleanly, KWD 3 decimals
A3: RPT-02 | B3: Outstanding invoices PDF | C3: P1 | D3: Logged in | E3: Reports then Outstanding, Export PDF | F3: PDF branded, aged buckets correct
A4: RPT-03 | B4: Tenant ledger | C4: P1 | D4: Tenant with history | E4: Open tenant then Ledger | F4: Chronological invoices + payments + running balance
A5: RPT-04 | B5: Filter by Property | C5: P1 | D5: Multiple props | E5: Reports then pick Property A, Generate | F5: Only Property A data
A6: RPT-05 | B6: Filter respects company isolation | C6: P0 | D6: Multi-co setup | E6: Admin of Co A then any report | F6: Only Co A data, never Co B

Sheet 11. Tenant Portal
A1: ID | B1: Title | C1: Priority | D1: Preconditions | E1: Steps | F1: Expected Result | G1: Actual Result | H1: Result | I1: Tester | J1: Date | K1: Bug ID | L1: Notes
A2: TP-01 | B2: Tenant login | C2: P0 | D2: Tenant credentials | E2: Visit /TenantPortal/Login then Sign in | F2: Tenant dashboard loads
A3: TP-02 | B3: Dashboard next rent due | C3: P0 | D3: Tenant with lease | E3: After login | F3: Amount + due date + days-to-due visible
A4: TP-03 | B4: View unpaid invoice | C4: P0 | D4: Unpaid invoice | E4: Invoices then open | F4: Amount, due date, Pay button visible
A5: TP-04 | B5: Pay with K-NET button visible | C5: P0 | D5: Unpaid invoice | E5: Same as TP-03 | F5: K-NET button present
A6: TP-05 | B6: Raise maintenance request | C6: P0 | D6: Tenant logged in | E6: Maintenance then New then Submit | F6: Request created
A7: TP-06 | B7: Upload tenant document | C7: P1 | D7: Tenant logged in | E7: Documents then Upload | F7: Document saved, visible in their list
A8: TP-07 | B8: View receipt PDF | C8: P1 | D8: Paid invoice | E8: Invoices then Paid then Download receipt | F8: Branded PDF
A9: TP-08 | B9: Cannot see other tenants data | C9: P0 | D9: Tenant A logged in | E9: URL /TenantPortal/Invoice/{B-invoice-id} | F9: 404 or 403

Sheet 12. Role-Based Access
A1: ID | B1: Title | C1: Priority | D1: Preconditions | E1: Steps | F1: Expected Result | G1: Actual Result | H1: Result | I1: Tester | J1: Date | K1: Bug ID | L1: Notes
A2: RBAC-01 | B2: Manager blocked from /Users | C2: P0 | D2: Logged in as Manager | E2: Try /Users | F2: 403 or hidden in sidebar
A3: RBAC-02 | B3: Manager blocked from /Payments | C3: P0 | D3: Logged in as Manager | E3: Try /Payments | F3: 403 or hidden in sidebar
A4: RBAC-03 | B4: Manager allowed /Properties | C4: P0 | D4: Logged in as Manager | E4: /Properties | F4: Allowed
A5: RBAC-04 | B5: Accountant view-only Maintenance | C5: P1 | D5: Logged in as Accountant | E5: /Maintenance | F5: View only (no create button)
A6: RBAC-05 | B6: Accountant allowed Reports | C6: P1 | D6: Logged in as Accountant | E6: /Reports | F6: Allowed
A7: RBAC-06 | B7: Accountant blocked from Audit | C7: P0 | D7: Logged in as Accountant | E7: /Audit | F7: 403
A8: RBAC-07 | B8: Admin allowed Hangfire | C8: P1 | D8: Logged in as Admin | E8: /hangfire | F8: Allowed
A9: RBAC-08 | B9: Manager blocked Hangfire | C9: P0 | D9: Logged in as Manager | E9: /hangfire | F9: 403
A10: RBAC-09 | B10: Tenant blocked staff dashboard | C10: P0 | D10: Logged in as Tenant | E10: /Dashboard | F10: 403 or redirect to tenant portal
A11: RBAC-10 | B11: Anon blocked from civilid API | C11: P0 | D11: Logged out | E11: GET /api/civilid/parse?id=... | F11: 401

Sheet 13. Edge Cases
A1: ID | B1: Title | C1: Priority | D1: Preconditions | E1: Steps | F1: Expected Result | G1: Actual Result | H1: Result | I1: Tester | J1: Date | K1: Bug ID | L1: Notes
A2: EDGE-01 | B2: XSS in tenant name | C2: P0 | D2: Logged in | E2: Tenant name = script-tag injection, Save, View list | F2: Saved literally, rendered escaped, no JS execution
A3: EDGE-02 | B3: SQL injection in search | C3: P0 | D3: Logged in | E3: Search: drop-table payload | F3: No error; tables intact
A4: EDGE-03 | B4: Long string overflow | C4: P1 | D4: New form | E4: FirstName = 500 chars | F4: Truncated or friendly error, not 500
A5: EDGE-04 | B5: Negative rent | C5: P1 | D5: New lease | E5: Rent = -100, Save | F5: Validation error
A6: EDGE-05 | B6: Payment in closed period | C6: P1 | D6: Closed period | E6: Try cash payment for closed period | F6: Blocked with reason
A7: EDGE-06 | B7: Unicode tenant name (Arabic) | C7: P1 | D7: New tenant | E7: Name = Arabic characters, Save | F7: Saved and displayed correctly
A8: EDGE-07 | B8: Future DOB | C8: P1 | D8: New tenant | E8: DOB = 2030-01-01 | F8: Validation error
A9: EDGE-08 | B9: Concurrent edit | C9: P2 | D9: Tenant exists | E9: Open same tenant in 2 tabs, Edit differently, Save both | F9: Stale-data warning OR last-write logged
A10: EDGE-09 | B10: Browser back after submit | C10: P2 | D10: On Create form | E10: Submit then Back button | F10: No duplicate submission
A11: EDGE-10 | B11: Session expiry mid-edit | C11: P2 | D11: On Create form | E11: Wait 13 hrs then Submit | F11: Redirect to login, no data loss (draft restored)

Sheet 14. Performance
A1: ID | B1: Title | C1: Priority | D1: Preconditions | E1: Steps | F1: Expected Result | G1: Actual Result | H1: Result | I1: Tester | J1: Date | K1: Bug ID | L1: Notes
A2: PERF-01 | B2: Login page first paint | C2: P1 | D2: Cold start | E2: Open /Account/Login | F2: Under 1.5s dev / 3s SmarterASP
A3: PERF-02 | B3: Dashboard load | C3: P1 | D3: Logged in | E3: Open /Dashboard | F3: Under 2s
A4: PERF-03 | B4: Tenant list 500+ rows | C4: P1 | D4: Logged in | E4: Open /Tenants | F4: Under 3s; pagination works
A5: PERF-04 | B5: Civil ID parse round-trip | C5: P1 | D5: On form | E5: Type 12-digit ID | F5: Under 500ms response
A6: PERF-05 | B6: Civil ID Gemini scan | C6: P1 | D6: Gemini enabled | E6: Upload Civil ID image | F6: Under 6s end-to-end
A7: PERF-06 | B7: Invoice PDF generation | C7: P1 | D7: Open invoice | E7: Download PDF | F7: Under 2s

Sheet 15. Cross-Browser
A1: Browser | B1: OS | C1: Smoke Pass | D1: Notes
A2: Chrome (latest) | B2: Windows 11
A3: Edge (latest) | B3: Windows 11
A4: Firefox (latest) | B4: Windows 11
A5: Safari (iOS 16+) | B5: iPhone
A6: Chrome (Android 12+) | B6: Android
